deduper/__init__.py
deduper/admin.py
deduper/apps.py
deduper/asgi.py
deduper/manage.py
deduper/models.py
deduper/settings.py
deduper/tests.py
deduper/urls.py
deduper/views.py
deduper/wsgi.py
deduper/deduplicate/__init__.py
deduper/deduplicate/admin.py
deduper/deduplicate/apps.py
deduper/deduplicate/models.py
deduper/deduplicate/process_requests.py
deduper/deduplicate/tests.py
deduper/deduplicate/urls.py
deduper/deduplicate/views.py
deduper/deduplicate/migrations/__init__.py
deduper/logs/__init__.py
deduper/logs/admin.py
deduper/logs/apps.py
deduper/logs/models.py
deduper/logs/tests.py
deduper/logs/urls.py
deduper/logs/views.py
deduper/logs/migrations/__init__.py
deduper/migrations/__init__.py
libs/__init__.py
libs/uuid.py
libs/connector/__init__.py
libs/connector/base_connector.py
libs/connector/dataframe_connector.py
libs/connector/generic_connector.py
libs/connector/postgres_connector.py
manglers/__init__.py
manglers/mangle_org_name.py
manglers/mangle_url.py
manglers/tld_swap_prob_dict.py
manglers/tests/__init__.py
manglers/tests/test_mangle_org.py
manglers/tests/test_mangle_url.py
manglers/tests/testing.py
silobuster_test/__init__.py
silobuster_test/libs/__init__.py
silobuster_test/libs/uuid.py
silobuster_test/libs/connector/__init__.py
silobuster_test/libs/connector/base_connector.py
silobuster_test/libs/connector/dataframe_connector.py
silobuster_test/libs/connector/generic_connector.py
silobuster_test/libs/connector/postgres_connector.py
silobuster_test-0.3.dist-info/METADATA
silobuster_test-0.3.dist-info/WHEEL
silobuster_test-0.3.dist-info/top_level.txt
silobuster_test-0.3.dist-info/RECORD
